Metadata-Version: 1.1
Name: pretty-dump
Version: 3.0
Summary: Diff and dump anything
Home-page: https://github.com/adfinis-sygroup/freeze
Author: Adfinis-SyGroup
Author-email: jean-louis.fuchs@adfinis-sygroup.ch
License: UNKNOWN
Keywords: freeze state hash sort compare unittest
Platform: UNKNOWN
Classifier: Development Status :: 5 - Production/Stable
Classifier: Environment :: Console
Classifier: Intended Audience :: Developers
Classifier: Intended Audience :: Education
Classifier: Intended Audience :: Information Technology
Classifier: License :: OSI Approved :: GNU Affero General Public License v3
Classifier: Natural Language :: English
Classifier: Operating System :: OS Independent
Classifier: Programming Language :: Python :: 2.6
Classifier: Programming Language :: Python :: 2.7
Classifier: Programming Language :: Python :: 3.3
Classifier: Programming Language :: Python :: 3.4
Classifier: Programming Language :: Python :: 3.5
Classifier: Topic :: Software Development :: Libraries
Classifier: Topic :: Scientific/Engineering :: Information Analysis
Classifier: Topic :: Software Development :: Testing
